jexia_cli/__init__.py
jexia_cli/base.py
jexia_cli/constants.py
jexia_cli/formatters.py
jexia_cli/shell.py
jexia_cli/utils.py
jexia_cli/commands/__init__.py
jexia_cli/commands/apps.py
jexia_cli/commands/apps_deployments.py
jexia_cli/commands/apps_domains.py
jexia_cli/commands/channels.py
jexia_cli/commands/datasets.py
jexia_cli/commands/datasets_fields.py
jexia_cli/commands/datasets_import_export.py
jexia_cli/commands/filesets.py
jexia_cli/commands/filesets_fields.py
jexia_cli/commands/keys.py
jexia_cli/commands/login.py
jexia_cli/commands/policies.py
jexia_cli/commands/projects.py
jexia_cli/commands/relations.py
jexia_cli/commands/use.py
jexia_cli/commands/usersets.py
tests/cli/__init__.py
tests/cli/test_apps.py
tests/cli/test_channels.py
tests/cli/test_datasets.py
tests/cli/test_filesets.py
tests/cli/test_keys.py
tests/cli/test_policies.py
tests/cli/test_projects.py
tests/cli/test_relations.py
tests/cli/test_usersets.py
jexia_cli-1.0.0.dist-info/METADATA
jexia_cli-1.0.0.dist-info/WHEEL
jexia_cli-1.0.0.dist-info/entry_points.txt
jexia_cli-1.0.0.dist-info/top_level.txt
jexia_cli-1.0.0.dist-info/RECORD
